2-Fnn_4layer_Design/Fnn_4layer_Design.v
module FNN(
    input wire clk,
    input wire reset,
    input wire [31:0] input_data,  // 4 inputs, each 8 bits
    output reg [31:0] output_data  // 4 outputs, each 8 bits
);

    // Number of neurons per layer
    parameter NEURONS = 4;

    // Define weights and biases for each layer (hardcoded as examples)
    reg [7:0] weights1[NEURONS-1:0][NEURONS-1:0];
    reg [7:0] biases1[NEURONS-1:0];

    reg [7:0] weights2[NEURONS-1:0][NEURONS-1:0];
    reg [7:0] biases2[NEURONS-1:0];

    reg [7:0] weights3[NEURONS-1:0][NEURONS-1:0];
    reg [7:0] biases3[NEURONS-1:0];

    reg [7:0] weights4[NEURONS-1:0][NEURONS-1:0];
    reg [7:0] biases4[NEURONS-1:0];

    // Intermediate signals
    reg [7:0] layer1_out[NEURONS-1:0];
    reg [7:0] layer2_out[NEURONS-1:0];
    reg [7:0] layer3_out[NEURONS-1:0];
    reg [7:0] layer4_out[NEURONS-1:0];

    integer i, j;

    // Initialize weights and biases
    initial begin
        // Layer 1 weights and biases
        weights1[0][0] = 8'h1; weights1[0][1] = 8'h2; weights1[0][2] = 8'h3; weights1[0][3] = 8'h4;
        biases1[0] = 8'h1;
        // Repeat initialization for other layers (weights2, biases2, etc.)
    end

    // Forward pass
    always @(posedge clk or posedge reset) begin
        if (reset) begin
            output_data <= 0;
        end else begin
            // Layer 1: Input to Layer 1
            for (i = 0; i < NEURONS; i = i + 1) begin
                layer1_out[i] = biases1[i];
                for (j = 0; j < NEURONS; j = j + 1) begin
                    layer1_out[i] = layer1_out[i] + (weights1[i][j] * input_data[8*j +: 8]);
                end
                layer1_out[i] = layer1_out[i] > 8'd0 ? layer1_out[i] : 8'd0; // ReLU
            end

            // Layer 2: Layer 1 to Layer 2
            for (i = 0; i < NEURONS; i = i + 1) begin
                layer2_out[i] = biases2[i];
                for (j = 0; j < NEURONS; j = j + 1) begin
                    layer2_out[i] = layer2_out[i] + (weights2[i][j] * layer1_out[j]);
                end
                layer2_out[i] = layer2_out[i] > 8'd0 ? layer2_out[i] : 8'd0; // ReLU
            end

            // Layer 3: Layer 2 to Layer 3
            for (i = 0; i < NEURONS; i = i + 1) begin
                layer3_out[i] = biases3[i];
                for (j = 0; j < NEURONS; j = j + 1) begin
                    layer3_out[i] = layer3_out[i] + (weights3[i][j] * layer2_out[j]);
                end
                layer3_out[i] = layer3_out[i] > 8'd0 ? layer3_out[i] : 8'd0; // ReLU
            end

            // Layer 4: Layer 3 to Layer 4 (Output Layer)
            for (i = 0; i < NEURONS; i = i + 1) begin
                layer4_out[i] = biases4[i];
                for (j = 0; j < NEURONS; j = j + 1) begin
                    layer4_out[i] = layer4_out[i] + (weights4[i][j] * layer3_out[j]);
                end
                layer4_out[i] = layer4_out[i] > 8'd0 ? layer4_out[i] : 8'd0; // ReLU
            end

            // Pack the output data
            for (i = 0; i < NEURONS; i = i + 1) begin
                output_data[8*i +: 8] = layer4_out[i];
            end
        end
    end
endmodule

2-Fnn_4layer_Design/Testbench.v
module FNN_tb;
    reg clk;
    reg reset;
    reg [31:0] input_data;
    wire [31:0] output_data;

    // Instantiate the FNN module
    FNN uut (
        .clk(clk),
        .reset(reset),
        .input_data(input_data),
        .output_data(output_data)
    );

    // Clock generation
    initial begin
        clk = 0;
        forever #5 clk = ~clk; // 10 ns clock period
    end

    // Test stimulus
    initial begin
        // Initialize signals
        reset = 1;
        input_data = 32'h0;
        #10;

        reset = 0;
        input_data = 32'h01020304; // Example input
        #100;

        input_data = 32'h05060708; // Another example input
        #100;

        $finish; // End simulation
    end

    // Waveform generation
    initial begin
        $dumpfile("fnn_waveform.vcd"); // VCD file to store waveforms
        $dumpvars(0, FNN_tb);          // Dump all variables in the testbench
    end
endmodule

Fnn_4layer_Design/fnn_waveform.vcd
$date
	Mon Dec 23 21:55:48 2024
$end
$version
	Icarus Verilog
$end
$timescale
	1s
$end
$scope module FNN_tb $end
$var wire 32 ! output_data [31:0] $end
$var reg 1 " clk $end
$var reg 32 # input_data [31:0] $end
$var reg 1 $ reset $end
$scope module uut $end
$var wire 1 " clk $end
$var wire 32 % input_data [31:0] $end
$var wire 1 $ reset $end
$var parameter 32 & NEURONS $end
$var reg 32 ' output_data [31:0] $end
$var integer 32 ( i [31:0] $end
$var integer 32 ) j [31:0] $end
$upscope $end
$upscope $end
$enddefinitions $end
$comment Show the parameter values. $end
$dumpall
b100 &
$end
#0
$dumpvars
bx )
bx (
b0 '
b0 %
1$
b0 #
0"
b0 !
$end
#5
1"
#10
0"
b1000000100000001100000100 #
b1000000100000001100000100 %
0$
#15
bx !
bx '
b100 )
b100 (
1"
#20
0"
#25
b100 )
b100 (
1"
#30
0"
#35
b100 )
b100 (
1"
#40
0"
#45
b100 )
b100 (
1"
#50
0"
#55
b100 )
b100 (
1"
#60
0"
#65
b100 )
b100 (
1"
#70
0"
#75
b100 )
b100 (
1"
#80
0"
#85
b100 )
b100 (
1"
#90
0"
#95
b100 )
b100 (
1"
#100
0"
#105
b100 )
b100 (
1"
#110
0"
b101000001100000011100001000 #
b101000001100000011100001000 %
#115
b100 )
b100 (
1"
#120
0"
#125
b100 )
b100 (
1"
#130
0"
#135
b100 )
b100 (
1"
#140
0"
#145
b100 )
b100 (
1"
#150
0"
#155
b100 )
b100 (
1"
#160
0"
#165
b100 )
b100 (
1"
#170
0"
#175
b100 )
b100 (
1"
#180
0"
#185
b100 )
b100 (
1"
#190
0"
#195
b100 )
b100 (
1"
#200
0"
#205
b100 )
b100 (
1"
