3-Pipelined_Multiplier/pipelined_multiplier.v
// 64-bit Pipelined Multiplier
module pipelined_multiplier (
    input clk,
    input rst,
    input [63:0] a,
    input [63:0] b,
    output reg [127:0] result
);

    reg [63:0] a_reg [0:3];
    reg [63:0] b_reg [0:3];
    reg [127:0] partial_products [0:3];

    always @(posedge clk or posedge rst) begin
        if (rst) begin
            a_reg[0] <= 64'd0;
            b_reg[0] <= 64'd0;
            partial_products[0] <= 128'd0;
            partial_products[1] <= 128'd0;
            partial_products[2] <= 128'd0;
            partial_products[3] <= 128'd0;
            result <= 128'd0;
        end else begin
            // Stage 1
            a_reg[0] <= a;
            b_reg[0] <= b;
            partial_products[0] <= a[31:0] * b[31:0];

            // Stage 2
            a_reg[1] <= a_reg[0];
            b_reg[1] <= b_reg[0];
            partial_products[1] <= a_reg[0][63:32] * b_reg[0][31:0] + partial_products[0];

            // Stage 3
            a_reg[2] <= a_reg[1];
            b_reg[2] <= b_reg[1];
            partial_products[2] <= a_reg[1][31:0] * b_reg[1][63:32] + partial_products[1];

            // Stage 4
            a_reg[3] <= a_reg[2];
            b_reg[3] <= b_reg[2];
            partial_products[3] <= a_reg[2][63:32] * b_reg[2][63:32] + partial_products[2];

            // Final result
            result <= partial_products[3];
        end
    end

endmodule

3-Pipelined_Multiplier/Testbench.v
// Testbench for 64-bit Pipelined Multiplier
module tb_pipelined_multiplier;

    reg clk;
    reg rst;
    reg [63:0] a;
    reg [63:0] b;
    wire [127:0] result;

    pipelined_multiplier uut (
        .clk(clk),
        .rst(rst),
        .a(a),
        .b(b),
        .result(result)
    );

    // Clock generation
    initial begin
        clk = 0;
        forever #5 clk = ~clk;
    end

    // Stimulus
    initial begin
        rst = 1;
        a = 0;
        b = 0;
        #10;
        rst = 0;

        // Test case 1
        a = 64'd15;
        b = 64'd10;
        #40;

        // Test case 2
        a = 64'd123456789;
        b = 64'd987654321;
        #40;

        // Test case 3
        a = 64'd0;
        b = 64'd9999;
        #40;

        // Test case 4
        a = 64'd18446744073709551615; // 2^64 - 1
        b = 64'd1;
        #40;

        $stop;
    end

    // Waveform generation
    initial begin
        $dumpfile("wave.vcd"); // 波形文件名
        $dumpvars(0, tb_pipelined_multiplier); // 保存的信号范围
    end

endmodule

Pipelined_Multiplier/wave.vcd
$date
	Mon Dec 23 22:41:40 2024
$end
$version
	Icarus Verilog
$end
$timescale
	1s
$end
$scope module tb_pipelined_multiplier $end
$var wire 128 ! result [127:0] $end
$var reg 64 " a [63:0] $end
$var reg 64 # b [63:0] $end
$var reg 1 $ clk $end
$var reg 1 % rst $end
$scope module uut $end
$var wire 64 & a [63:0] $end
$var wire 64 ' b [63:0] $end
$var wire 1 $ clk $end
$var wire 1 % rst $end
$var reg 128 ( result [127:0] $end
$upscope $end
$upscope $end
$enddefinitions $end
$comment Show the parameter values. $end
$dumpall
$end
#0
$dumpvars
b0 (
b0 '
b0 &
1%
0$
b0 #
b0 "
b0 !
$end
#5
1$
#10
0$
b1010 #
b1010 '
b1111 "
b1111 &
0%
#15
1$
#20
0$
#25
bx !
bx (
1$
#30
0$
#35
1$
#40
0$
#45
b0 !
b0 (
1$
#50
0$
b111010110111100110100010110001 #
b111010110111100110100010110001 '
b111010110111100110100010101 "
b111010110111100110100010101 &
#55
b10010110 !
b10010110 (
1$
#60
0$
#65
1$
#70
0$
#75
1$
#80
0$
#85
1$
#90
0$
b10011100001111 #
b10011100001111 '
b0 "
b0 &
#95
b110110001001100010001010011111011111111110101001110000101 !
b110110001001100010001010011111011111111110101001110000101 (
1$
#100
0$
#105
1$
#110
0$
#115
1$
#120
0$
#125
1$
#130
0$
b1 #
b1 '
b1111111111111111111111111111111111111111111111111111111111111111 "
b1111111111111111111111111111111111111111111111111111111111111111 &
#135
b0 !
b0 (
1$
